fluke_28x_dmm_util/__init__.py
fluke_28x_dmm_util/__main__.py
fluke_28x_dmm_util/dmm_util.py
fluke_28x_dmm_util-0.3.8.dist-info/LICENSE
fluke_28x_dmm_util-0.3.8.dist-info/METADATA
fluke_28x_dmm_util-0.3.8.dist-info/WHEEL
fluke_28x_dmm_util-0.3.8.dist-info/top_level.txt
fluke_28x_dmm_util-0.3.8.dist-info/RECORD
