Metadata-Version: 2.1
Name: fluke-28x-dmm-util
Version: 0.3.8
Summary: Utility for interacting with Fluke 289 and 287 Series multimeters.
Home-page: https://github.com/N0ury/dmm_util
Author: N0ury
License: MIT
Platform: UNKNOWN
Classifier: License :: OSI Approved :: MIT License
Classifier: Programming Language :: Python :: 3.10
Requires-Python: >=3.10
License-File: LICENSE
Requires-Dist: pyserial
